turning_points/__init__.py
turning_points/turning_points.py
turning_points-0.0.5.dist-info/WHEEL
turning_points-0.0.5.dist-info/METADATA
turning_points-0.0.5.dist-info/RECORD
