Metadata-Version: 2.1
Name: turning_points
Version: 0.0.5
Summary: A package to find turing points in tracks, andd plot
Keywords: trajectory-analysis,turning-points,transition-probabilities,data-science
Author-email: Charles Fosseprez <charles.fosseprez.me@gmail.com>
Requires-Python: >=3.8
Classifier: Programming Language :: Python :: 3
Classifier: License :: OSI Approved :: MIT License
Classifier: Operating System :: OS Independent
Requires-Dist: colorama==0.4.6
Requires-Dist: contourpy==1.2.1
Requires-Dist: cycler==0.12.1
Requires-Dist: exceptiongroup==1.2.0
Requires-Dist: fonttools==4.50.0
Requires-Dist: importlib_resources==6.4.0
Requires-Dist: iniconfig==2.0.0
Requires-Dist: kiwisolver==1.4.5
Requires-Dist: matplotlib==3.8.4
Requires-Dist: numpy==1.26.4
Requires-Dist: packaging==24.0
Requires-Dist: pillow==10.3.0
Requires-Dist: pluggy==1.4.0
Requires-Dist: pyparsing==3.1.2
Requires-Dist: pytest==8.1.1
Requires-Dist: python-dateutil==2.9.0.post0
Requires-Dist: scipy==1.13.0
Requires-Dist: six==1.16.0
Requires-Dist: tomli==2.0.1
Requires-Dist: zipp==3.18.1
Project-URL: Homepage, https://github.com/lesptizami/turning_points
Project-URL: Issues, https://github.com/lesptizami/turning_points/issues
